uc/__init__.py
uc/scraper.py
uc/utils.py
uc_scraper-0.2.dist-info/LICENSE
uc_scraper-0.2.dist-info/METADATA
uc_scraper-0.2.dist-info/WHEEL
uc_scraper-0.2.dist-info/top_level.txt
uc_scraper-0.2.dist-info/RECORD
