Metadata-Version: 2.1
Name: uc-scraper
Version: 0.2
Summary: A scraper of statistical data from uc.se, built on top of Statscraper.
Home-page: https://github.com/jplusplus/uc_scraper
Author: Jens Finnäs
Author-email: jens.finnas@gmail.com
License: MIT
Download-URL: https://github.com/jplusplus/uc_scraper/archive/0.2.tar.gz
Platform: UNKNOWN
Requires-Dist: statscraper
Requires-Dist: requests
Requires-Dist: beautifulsoup4
